MANIFEST.in
README.rst
setup.py
bin/shuttertalk
shuttertalk/__init__.py
slidepull.egg-info/PKG-INFO
slidepull.egg-info/SOURCES.txt
slidepull.egg-info/dependency_links.txt
slidepull.egg-info/requires.txt
slidepull.egg-info/top_level.txt