Metadata-Version: 1.0
Name: slidepull
Version: 0.12
Summary: something
Home-page: http://alden.life
Author: Alden
Author-email: rivendalejones@gmail.com
License: GPL
Platform: UNKNOWN
